{
  "width": 102,
  "height": 26,
  "stations": [
    {
      "from": [6, 3],
      "to": [7, 22]
    },
    {
      "from": [10, 3],
      "to": [11, 22]
    },
    {
      "from": [14, 3],
      "to": [15, 22]
    }
  ],
  "delivery": [
    {
      "from": [2, 3],
      "to": [3, 22]
    }
  ],
  "shelves": [
    {
      "from": [18, 2],
      "to": [19, 3]
    },
    {
      "from": [22, 2],
      "to": [29, 3]
    },
    {
      "from": [32, 2],
      "to": [33, 3]
    },
    {
      "from": [36, 2],
      "to": [43, 3]
    },
    {
      "from": [46, 2],
      "to": [47, 3]
    },
    {
      "from": [50, 2],
      "to": [57, 3]
    },
    {
      "from": [60, 2],
      "to": [61, 3]
    },
    {
      "from": [64, 2],
      "to": [71, 3]
    },
    {
      "from": [74, 2],
      "to": [75, 3]
    },
    {
      "from": [78, 2],
      "to": [85, 3]
    },
    {
      "from": [88, 2],
      "to": [89, 3]
    },
    {
      "from": [92, 2],
      "to": [99, 3]
    },
    {
      "from": [18, 6],
      "to": [19, 7]
    },
    {
      "from": [22, 6],
      "to": [29, 7]
    },
    {
      "from": [32, 6],
      "to": [33, 7]
    },
    {
      "from": [36, 6],
      "to": [43, 7]
    },
    {
      "from": [46, 6],
      "to": [47, 7]
    },
    {
      "from": [50, 6],
      "to": [57, 7]
    },
    {
      "from": [60, 6],
      "to": [61, 7]
    },
    {
      "from": [64, 6],
      "to": [71, 7]
    },
    {
      "from": [74, 6],
      "to": [75, 7]
    },
    {
      "from": [78, 6],
      "to": [85, 7]
    },
    {
      "from": [88, 6],
      "to": [89, 7]
    },
    {
      "from": [92, 6],
      "to": [99, 7]
    },
    {
      "from": [18, 10],
      "to": [19, 11]
    },
    {
      "from": [22, 10],
      "to": [29, 11]
    },
    {
      "from": [32, 10],
      "to": [33, 11]
    },
    {
      "from": [36, 10],
      "to": [43, 11]
    },
    {
      "from": [46, 10],
      "to": [47, 11]
    },
    {
      "from": [50, 10],
      "to": [57, 11]
    },
    {
      "from": [60, 10],
      "to": [61, 11]
    },
    {
      "from": [64, 10],
      "to": [71, 11]
    },
    {
      "from": [74, 10],
      "to": [75, 11]
    },
    {
      "from": [78, 10],
      "to": [85, 11]
    },
    {
      "from": [88, 10],
      "to": [89, 11]
    },
    {
      "from": [92, 10],
      "to": [99, 11]
    },
    {
      "from": [18, 14],
      "to": [19, 15]
    },
    {
      "from": [22, 14],
      "to": [29, 15]
    },
    {
      "from": [32, 14],
      "to": [33, 15]
    },
    {
      "from": [36, 14],
      "to": [43, 15]
    },
    {
      "from": [46, 14],
      "to": [47, 15]
    },
    {
      "from": [50, 14],
      "to": [57, 15]
    },
    {
      "from": [60, 14],
      "to": [61, 15]
    },
    {
      "from": [64, 14],
      "to": [71, 15]
    },
    {
      "from": [74, 14],
      "to": [75, 15]
    },
    {
      "from": [78, 14],
      "to": [85, 15]
    },
    {
      "from": [88, 14],
      "to": [89, 15]
    },
    {
      "from": [92, 14],
      "to": [99, 15]
    },
    {
      "from": [18, 18],
      "to": [19, 19]
    },
    {
      "from": [22, 18],
      "to": [29, 19]
    },
    {
      "from": [32, 18],
      "to": [33, 19]
    },
    {
      "from": [36, 18],
      "to": [43, 19]
    },
    {
      "from": [46, 18],
      "to": [47, 19]
    },
    {
      "from": [50, 18],
      "to": [57, 19]
    },
    {
      "from": [60, 18],
      "to": [61, 19]
    },
    {
      "from": [64, 18],
      "to": [71, 19]
    },
    {
      "from": [74, 18],
      "to": [75, 19]
    },
    {
      "from": [78, 18],
      "to": [85, 19]
    },
    {
      "from": [88, 18],
      "to": [89, 19]
    },
    {
      "from": [92, 18],
      "to": [99, 19]
    },
    {
      "from": [18, 22],
      "to": [19, 23]
    },
    {
      "from": [22, 22],
      "to": [29, 23]
    },
    {
      "from": [32, 22],
      "to": [33, 23]
    },
    {
      "from": [36, 22],
      "to": [43, 23]
    },
    {
      "from": [46, 22],
      "to": [47, 23]
    },
    {
      "from": [50, 22],
      "to": [57, 23]
    },
    {
      "from": [60, 22],
      "to": [61, 23]
    },
    {
      "from": [64, 22],
      "to": [71, 23]
    },
    {
      "from": [74, 22],
      "to": [75, 23]
    },
    {
      "from": [78, 22],
      "to": [85, 23]
    },
    {
      "from": [88, 22],
      "to": [89, 23]
    },
    {
      "from": [92, 22],
      "to": [99, 23]
    }
  ]
}
